mermaid_sns_sqs_graph/__init__.py
mermaid_sns_sqs_graph/aws_helper.py
mermaid_sns_sqs_graph/main.py
mermaid_sns_sqs_graph/mermaid_helper.py
mermaid_sns_sqs_graph-0.1.3.dist-info/METADATA
mermaid_sns_sqs_graph-0.1.3.dist-info/WHEEL
mermaid_sns_sqs_graph-0.1.3.dist-info/entry_points.txt
mermaid_sns_sqs_graph-0.1.3.dist-info/top_level.txt
mermaid_sns_sqs_graph-0.1.3.dist-info/RECORD
