Metadata-Version: 2.4
Name: mermaid-sns-sqs-graph
Version: 0.1.3
Summary: Utility to map the sns sqs connections
Author: Gaurav soni
Requires-Python: >=3.8
Requires-Dist: boto3>=1.40.66
